[
  {
    "id": 1,
    "match_id": 1,
    "goal_volume_score": 25,
    "goal_timing_score": 8,
    "goal_distribution_score": 2,
    "total_score": 35,
    "rating_category": "Good",
    "created_at": "2025-09-19T01:38:50.774Z"
  },
  {
    "id": 2,
    "match_id": 2,
    "goal_volume_score": 25,
    "goal_timing_score": 8,
    "goal_distribution_score": 15,
    "total_score": 48,
    "rating_category": "Good",
    "created_at": "2025-09-19T01:38:50.777Z"
  },
  {
    "id": 3,
    "match_id": 3,
    "goal_volume_score": 0,
    "goal_timing_score": 0,
    "goal_distribution_score": 0,
    "total_score": 0,
    "rating_category": "Very Poor",
    "created_at": "2025-09-19T01:38:50.782Z"
  },
  {
    "id": 4,
    "match_id": 4,
    "goal_volume_score": 0,
    "goal_timing_score": 0,
    "goal_distribution_score": 0,
    "total_score": 0,
    "rating_category": "Very Poor",
    "created_at": "2025-09-19T01:38:50.785Z"
  },
  {
    "id": 5,
    "match_id": 5,
    "goal_volume_score": 5,
    "goal_timing_score": 3,
    "goal_distribution_score": 0,
    "total_score": 8,
    "rating_category": "Very Poor",
    "created_at": "2025-09-19T01:38:50.790Z"
  },
  {
    "id": 6,
    "match_id": 6,
    "goal_volume_score": 5,
    "goal_timing_score": 0,
    "goal_distribution_score": 0,
    "total_score": 5,
    "rating_category": "Very Poor",
    "created_at": "2025-09-19T01:38:50.794Z"
  },
  {
    "id": 7,
    "match_id": 7,
    "goal_volume_score": 25,
    "goal_timing_score": 3,
    "goal_distribution_score": 0,
    "total_score": 28,
    "rating_category": "Average",
    "created_at": "2025-09-19T01:38:50.798Z"
  },
  {
    "id": 8,
    "match_id": 8,
    "goal_volume_score": 35,
    "goal_timing_score": 6,
    "goal_distribution_score": 18,
    "total_score": 59,
    "rating_category": "Good",
    "created_at": "2025-09-19T01:38:50.801Z"
  },
  {
    "id": 9,
    "match_id": 9,
    "goal_volume_score": 5,
    "goal_timing_score": 3,
    "goal_distribution_score": 0,
    "total_score": 8,
    "rating_category": "Very Poor",
    "created_at": "2025-09-19T01:38:50.805Z"
  },
  {
    "id": 10,
    "match_id": 10,
    "goal_volume_score": 25,
    "goal_timing_score": 8,
    "goal_distribution_score": 2,
    "total_score": 35,
    "rating_category": "Good",
    "created_at": "2025-09-19T01:38:50.809Z"
  },
  {
    "id": 11,
    "match_id": 11,
    "goal_volume_score": 15,
    "goal_timing_score": 0,
    "goal_distribution_score": 0,
    "total_score": 15,
    "rating_category": "Average",
    "created_at": "2025-09-19T01:38:50.812Z"
  },
  {
    "id": 12,
    "match_id": 12,
    "goal_volume_score": 35,
    "goal_timing_score": 6,
    "goal_distribution_score": 25,
    "total_score": 66,
    "rating_category": "REALLY Good",
    "created_at": "2025-09-19T01:38:50.815Z"
  },
  {
    "id": 13,
    "match_id": 13,
    "goal_volume_score": 50,
    "goal_timing_score": 8,
    "goal_distribution_score": 25,
    "total_score": 83,
    "rating_category": "AMAZING",
    "created_at": "2025-09-19T01:38:50.818Z"
  },
  {
    "id": 14,
    "match_id": 14,
    "goal_volume_score": 45,
    "goal_timing_score": 0,
    "goal_distribution_score": 25,
    "total_score": 70,
    "rating_category": "REALLY Good",
    "created_at": "2025-09-19T01:38:50.822Z"
  },
  {
    "id": 15,
    "match_id": 15,
    "goal_volume_score": 5,
    "goal_timing_score": 0,
    "goal_distribution_score": 0,
    "total_score": 5,
    "rating_category": "Very Poor",
    "created_at": "2025-09-19T01:38:50.825Z"
  },
  {
    "id": 16,
    "match_id": 16,
    "goal_volume_score": 25,
    "goal_timing_score": 0,
    "goal_distribution_score": 22,
    "total_score": 47,
    "rating_category": "Good",
    "created_at": "2025-09-19T01:38:50.828Z"
  },
  {
    "id": 17,
    "match_id": 17,
    "goal_volume_score": 35,
    "goal_timing_score": 10,
    "goal_distribution_score": 25,
    "total_score": 70,
    "rating_category": "REALLY Good",
    "created_at": "2025-09-19T01:38:50.833Z"
  },
  {
    "id": 18,
    "match_id": 18,
    "goal_volume_score": 0,
    "goal_timing_score": 0,
    "goal_distribution_score": 0,
    "total_score": 0,
    "rating_category": "Very Poor",
    "created_at": "2025-09-19T01:38:50.837Z"
  },
  {
    "id": 19,
    "match_id": 19,
    "goal_volume_score": 15,
    "goal_timing_score": 5,
    "goal_distribution_score": 2,
    "total_score": 22,
    "rating_category": "Average",
    "created_at": "2025-09-19T01:38:50.842Z"
  },
  {
    "id": 20,
    "match_id": 20,
    "goal_volume_score": 45,
    "goal_timing_score": 8,
    "goal_distribution_score": 25,
    "total_score": 78,
    "rating_category": "AMAZING",
    "created_at": "2025-09-19T01:38:50.846Z"
  },
  {
    "id": 21,
    "match_id": 21,
    "goal_volume_score": 35,
    "goal_timing_score": 10,
    "goal_distribution_score": 4,
    "total_score": 49,
    "rating_category": "Good",
    "created_at": "2025-09-19T01:38:50.851Z"
  },
  {
    "id": 22,
    "match_id": 22,
    "goal_volume_score": 35,
    "goal_timing_score": 6,
    "goal_distribution_score": 25,
    "total_score": 66,
    "rating_category": "REALLY Good",
    "created_at": "2025-09-19T01:38:50.857Z"
  },
  {
    "id": 23,
    "match_id": 23,
    "goal_volume_score": 35,
    "goal_timing_score": 3,
    "goal_distribution_score": 18,
    "total_score": 56,
    "rating_category": "Good",
    "created_at": "2025-09-19T01:38:50.860Z"
  },
  {
    "id": 24,
    "match_id": 24,
    "goal_volume_score": 45,
    "goal_timing_score": 5,
    "goal_distribution_score": 25,
    "total_score": 75,
    "rating_category": "AMAZING",
    "created_at": "2025-09-19T01:38:50.864Z"
  },
  {
    "id": 25,
    "match_id": 25,
    "goal_volume_score": 25,
    "goal_timing_score": 0,
    "goal_distribution_score": 22,
    "total_score": 47,
    "rating_category": "Good",
    "created_at": "2025-09-19T01:38:50.870Z"
  },
  {
    "id": 26,
    "match_id": 26,
    "goal_volume_score": 15,
    "goal_timing_score": 0,
    "goal_distribution_score": 0,
    "total_score": 15,
    "rating_category": "Average",
    "created_at": "2025-09-19T01:38:50.876Z"
  },
  {
    "id": 27,
    "match_id": 27,
    "goal_volume_score": 50,
    "goal_timing_score": 6,
    "goal_distribution_score": 15,
    "total_score": 71,
    "rating_category": "REALLY Good",
    "created_at": "2025-09-19T01:38:50.879Z"
  },
  {
    "id": 28,
    "match_id": 28,
    "goal_volume_score": 45,
    "goal_timing_score": 11,
    "goal_distribution_score": 25,
    "total_score": 81,
    "rating_category": "AMAZING",
    "created_at": "2025-09-19T01:38:50.912Z"
  }
]